{
  "parent": "minecraft:item/generated",
  "overrides": [
    {
      "model": "thecondimentmod:item/pepper_chest_quartz_trim",
      "predicate": {
        "minecraft:trim_type": 0.1
      }
    },
    {
      "model": "thecondimentmod:item/pepper_chest_iron_trim",
      "predicate": {
        "minecraft:trim_type": 0.2
      }
    },
    {
      "model": "thecondimentmod:item/pepper_chest_netherite_trim",
      "predicate": {
        "minecraft:trim_type": 0.3
      }
    },
    {
      "model": "thecondimentmod:item/pepper_chest_redstone_trim",
      "predicate": {
        "minecraft:trim_type": 0.4
      }
    },
    {
      "model": "thecondimentmod:item/pepper_chest_copper_trim",
      "predicate": {
        "minecraft:trim_type": 0.5
      }
    },
    {
      "model": "thecondimentmod:item/pepper_chest_gold_trim",
      "predicate": {
        "minecraft:trim_type": 0.6
      }
    },
    {
      "model": "thecondimentmod:item/pepper_chest_emerald_trim",
      "predicate": {
        "minecraft:trim_type": 0.7
      }
    },
    {
      "model": "thecondimentmod:item/pepper_chest_diamond_trim",
      "predicate": {
        "minecraft:trim_type": 0.8
      }
    },
    {
      "model": "thecondimentmod:item/pepper_chest_lapis_trim",
      "predicate": {
        "minecraft:trim_type": 0.9
      }
    },
    {
      "model": "thecondimentmod:item/pepper_chest_amethyst_trim",
      "predicate": {
        "minecraft:trim_type": 1.0
      }
    }
  ],
  "textures": {
    "layer0": "thecondimentmod:item/pepper_chest"
  }
}